{
  "name": "Mario Kart 8",
  "icon": "https://cdn2.steamgriddb.com/icon_thumb/ac1ad983e08ad3304a97e147f522747e.png",
  "titleIds": [
    "000500001010EB00",
    "000500001010EC00",
    "000500001010ED00"
  ],
  "mods": [
    {
      "id": "kermit-mk8",
      "name": "Kermit the Frog",
      "type": "mod",
      "version": "1.0.0",
      "author": "Crashbandiboy2222",
      "description": "Kermit the Frog joins Mario Kart 8! Including a little surprise over Metal Mario. The model is from Band-Aid Magic Vison. I'm not sure what that is or who exactly made the model. I did edit the textures though.",
      "thumbnail": "https://images.gamebanana.com/img/ss/mods/68a3a85c81fc9.jpg",
      "screenshots": [
        "https://images.gamebanana.com/img/ss/mods/68a3a87c96dec.jpg",
        "https://images.gamebanana.com/img/ss/mods/68a3a87ca7b95.jpg",
        "https://images.gamebanana.com/img/ss/mods/68a3a87c821f2.jpg",
        "https://images.gamebanana.com/img/ss/mods/68a3a87c2bc3e.jpg",
        "https://images.gamebanana.com/img/ss/mods/68a3a87c745d1.jpg"
      ],
      "download": "https://github.com/daniel6day/coffeeshop-repo-template/releases/download/mod-files/kermit_d7c77.zip",
      "releaseDate": "2024-03-10",
      "license": "CC BY-NC-ND",
      "tags": ["skin"],
      "fileSize": 3580000,
      "changelog": "1.0.0 - Initial release"
    },
    {
     "id": "spongebob",
      "name": "Spongebob Squarepants",
      "type": "mod",
      "version": "1.0.0",
      "author": "Kalomaze",
      "description": "Spongebob Joins Mario Kart 8!\nReplaces Lakitu",
      "thumbnail": "https://images.gamebanana.com/img/ss/mods/5acea99f84ff7.jpg",
      "screenshots": [
        "https://images.gamebanana.com/img/ss/mods/5aceaeec5e0b0.jpg",
        "https://images.gamebanana.com/img/ss/mods/5aceaf03b6aa0.jpg",
        "https://images.gamebanana.com/img/ss/mods/5aceaec889b71.jpg"
      ],
      "download": "https://github.com/daniel6day/coffeeshop-repo-template/releases/download/mod-files/spongebobmk8.zip",
      "releaseDate": "2018-04-12",
      "license": "CC BY-NC-ND",
      "tags": ["skin"],
      "fileSize": 1800000,
      "requirements": [],
      "changelog": "1.0.0 - Initial release"
    },
    {
     "id": "Kratos",
      "name": "Kratos",
      "type": "mod",
      "version": "1.0.0",
      "author": "Gacsan & TrDankz",
      "description": "Kratos Joins the race.\nReplaces Lakitu",
      "thumbnail": "https://images.gamebanana.com/img/ss/mods/530-90_6893d1aab786a.jpg",
      "screenshots": [
        "https://images.gamebanana.com/img/ss/mods/684103db5719e.jpg",
        "https://images.gamebanana.com/img/ss/mods/68410446448d1.jpg",
        "https://images.gamebanana.com/img/ss/mods/6841045957094.jpg",
        "https://images.gamebanana.com/img/ss/mods/6841046983569.jpg"
      ],
      "download": "https://github.com/daniel6day/coffeeshop-repo-template/releases/download/mod-files/kratos_over_dry_bowser.rar",
      "releaseDate": "2025-06-05",
      "license": "CC BY-NC-ND",
      "tags": ["skin"],
      "fileSize": 2500000,
      "requirements": [],
      "changelog": "1.0.0 - Initial release"
    },
    {
      "id": "spamton",
      "name": "Spamton G Spamton",
      "type": "mod",
      "version": "1.0.0",
      "author": "BindyCot",
      "description": "Hey every! Spamton G. Spamton joins the race! replaces Baby Luigi",
      "thumbnail": "https://images.gamebanana.com/img/ss/mods/6158ae332b5b3.jpg",
      "screenshots": [
        "https://images.gamebanana.com/img/ss/mods/6158ae411723e.jpg",
        "https://images.gamebanana.com/img/ss/mods/6158ae4945730.jpg"
      ],
      "download": "https://github.com/daniel6day/coffeeshop-repo-template/releases/download/mod-files/spamton.zip",
      "releaseDate": "2021-10-02",
      "license": "CC BY-NC-ND",
      "tags": ["skin"],
      "fileSize": 999000,
      "changelog": "1.0.0 - Initial release"
    },
    {
      "id": "ultimate-bundle",
      "name": "Ultimate MK8 Bundle",
      "type": "modpack",
      "version": "1.0.0",
      "author": "ExampleUser",
      "description": "A curated bundle combining the Custom Music Pack and Retro Track Textures into one install.",
      "thumbnail": "https://picsum.photos/seed/mk8bundle/400/225",
      "screenshots": [
        "https://picsum.photos/seed/mk8bundlea/800/450"
      ],
      "includes": [
        "custom-music-pack",
        "retro-track-pack"
      ],
      "download": "https://github.com/timkicker/cupstore-repo-template/releases/download/dummy-testing/dummy-mod-mk8.zip",
      "releaseDate": "2024-04-01",
      "tags": ["music", "course", "texture"],
      "fileSize": 62914560
    }
  ]
}
